<DataTemplates>
  <DataTemplate>
    <ID>453</ID>
    <Name>DTManageMeetingsUser</Name>
    <AppID>0</AppID>
    <Label>Manage Meeting User</Label>
    <StructureName>vSysUsersWH</StructureName>
    <ConnID>1</ConnID>
    <FormTemplate />
    <ColumnTemplates />
    <RowAttributes />
    <DTType>SYSTEM</DTType>
    <ScreenId />
    <ObjectId />
    <Mode />
    <User />
    <RowsInGrid>0</RowsInGrid>
    <UseDTConnection>True</UseDTConnection>
    <ParentAppID>0</ParentAppID>
    <ParentDTID>0</ParentDTID>
    <HasClientSideExpressions>False</HasClientSideExpressions>
    <InMemory>False</InMemory>
    <ViewStyle>0</ViewStyle>
    <UpdatedBy>Admin</UpdatedBy>
    <UpdatedOn>2019-04-01 05:17:28.1630</UpdatedOn>
    <DTHelp />
    <IsStickyFields>False</IsStickyFields>
    <DTFields>
      <DTField>
        <Name>username</Name>
        <AllowNull>False</AllowNull>
        <DataType>System.String</DataType>
        <DefaultValue />
        <Label>User Name</Label>
        <MaxLength>50</MaxLength>
        <Ordinal>0</Ordinal>
        <ReadOnly>False</ReadOnly>
        <Required>True</Required>
        <Visible>TRUE</Visible>
        <DisplayID>USERID</DisplayID>
        <AppGroup>0</AppGroup>
        <Format />
        <LabelPosition>0</LabelPosition>
        <LabelAlign>0</LabelAlign>
        <PrimaryKey>True</PrimaryKey>
        <IsDBField>True</IsDBField>
        <InputInGrid>False</InputInGrid>
        <SearchType />
        <ColumnIndex>0</ColumnIndex>
        <Columns>0</Columns>
        <Hidden>FALSE</Hidden>
        <Value />
        <InUse>False</InUse>
        <NoWrap>False</NoWrap>
        <Group>0</Group>
        <Aggregate />
        <Align />
        <DTFieldHelp />
        <IsStickyField>False</IsStickyField>
        <DisplayType>
          <Name />
          <Label>- None -</Label>
          <AssemblyDLL>Made4Net.WebControls.dll</AssemblyDLL>
          <Class>Made4Net.WebControls.DisplayTypes.TextBox</Class>
        </DisplayType>
        <Properties />
      </DTField>
      <DTField>
        <Name>FULLNAME</Name>
        <AllowNull>True</AllowNull>
        <DataType>System.String</DataType>
        <DefaultValue />
        <Label>FULLNAME</Label>
        <MaxLength>100</MaxLength>
        <Ordinal>3</Ordinal>
        <ReadOnly>False</ReadOnly>
        <Required>False</Required>
        <Visible>TRUE</Visible>
        <DisplayID>FULLNAME</DisplayID>
        <AppGroup>0</AppGroup>
        <Format />
        <LabelPosition>0</LabelPosition>
        <LabelAlign>0</LabelAlign>
        <PrimaryKey>False</PrimaryKey>
        <IsDBField>True</IsDBField>
        <InputInGrid>False</InputInGrid>
        <SearchType />
        <ColumnIndex>0</ColumnIndex>
        <Columns>0</Columns>
        <Hidden>FALSE</Hidden>
        <Value />
        <InUse>False</InUse>
        <NoWrap>False</NoWrap>
        <Group>0</Group>
        <Aggregate />
        <Align />
        <DTFieldHelp />
        <IsStickyField>False</IsStickyField>
        <DisplayType>
          <Name />
          <Label>- None -</Label>
          <AssemblyDLL>Made4Net.WebControls.dll</AssemblyDLL>
          <Class>Made4Net.WebControls.DisplayTypes.TextBox</Class>
        </DisplayType>
        <Properties />
      </DTField>
    </DTFields>
    <Expressions />
  </DataTemplate>
</DataTemplates>